MdbookZhongwenWendangFix1/README.md
MdbookZhongwenWendangFix1/__init__.py
MdbookZhongwenWendangFix1/__main__.py
MdbookZhongwenWendangFix1/file.epub
MdbookZhongwenWendangFix1/index.html
MdbookZhongwenWendangFix1/css/__init__.py
MdbookZhongwenWendangFix1/css/annotations.css
MdbookZhongwenWendangFix1/css/main.css
MdbookZhongwenWendangFix1/css/normalize.css
MdbookZhongwenWendangFix1/css/popup.css
MdbookZhongwenWendangFix1/font/__init__.py
MdbookZhongwenWendangFix1/font/fontello.eot
MdbookZhongwenWendangFix1/font/fontello.svg
MdbookZhongwenWendangFix1/font/fontello.ttf
MdbookZhongwenWendangFix1/font/fontello.woff
MdbookZhongwenWendangFix1/img/__init__.py
MdbookZhongwenWendangFix1/img/annotator-glyph-sprite.png
MdbookZhongwenWendangFix1/img/annotator-icon-sprite.png
MdbookZhongwenWendangFix1/img/apple-touch-icon.png
MdbookZhongwenWendangFix1/img/cancelfullscreen.png
MdbookZhongwenWendangFix1/img/close.png
MdbookZhongwenWendangFix1/img/fullscreen.png
MdbookZhongwenWendangFix1/img/loader.gif
MdbookZhongwenWendangFix1/img/menu-icon.png
MdbookZhongwenWendangFix1/img/save.png
MdbookZhongwenWendangFix1/img/saved.png
MdbookZhongwenWendangFix1/img/settings-s.png
MdbookZhongwenWendangFix1/img/settings.png
MdbookZhongwenWendangFix1/img/star.png
MdbookZhongwenWendangFix1/js/__init__.py
MdbookZhongwenWendangFix1/js/epub.js
MdbookZhongwenWendangFix1/js/epub.min.js
MdbookZhongwenWendangFix1/js/epub.min.map
MdbookZhongwenWendangFix1/js/hooks.min.js
MdbookZhongwenWendangFix1/js/hooks.min.map
MdbookZhongwenWendangFix1/js/reader.js
MdbookZhongwenWendangFix1/js/reader.js.map
MdbookZhongwenWendangFix1/js/reader.min.js
MdbookZhongwenWendangFix1/js/reader.min.map
MdbookZhongwenWendangFix1/js/hooks/__init__.py
MdbookZhongwenWendangFix1/js/hooks/extensions/__init__.py
MdbookZhongwenWendangFix1/js/hooks/extensions/highlight.js
MdbookZhongwenWendangFix1/js/libs/__init__.py
MdbookZhongwenWendangFix1/js/libs/jquery.min.js
MdbookZhongwenWendangFix1/js/libs/localforage.min.js
mdbook_zhongwen_wendang_fix1-2025.3.25.0.dist-info/METADATA
mdbook_zhongwen_wendang_fix1-2025.3.25.0.dist-info/WHEEL
mdbook_zhongwen_wendang_fix1-2025.3.25.0.dist-info/entry_points.txt
mdbook_zhongwen_wendang_fix1-2025.3.25.0.dist-info/top_level.txt
mdbook_zhongwen_wendang_fix1-2025.3.25.0.dist-info/RECORD
